vdwlib/__init__.py
vdwlib/__version__.py
vdwlib/_radii.so
vdwlib/radii.py
vdwlib/descriptors/__init__.py
vdwlib/descriptors/_monte_carlo_based.so
vdwlib/descriptors/_sterimol.so
vdwlib/descriptors/_voxel_based.so
vdwlib/descriptors/monte_carlo_based.py
vdwlib/descriptors/sterimol.py
vdwlib/descriptors/voxel_based.py
vdwlib-0.3.0.dist-info/METADATA
vdwlib-0.3.0.dist-info/WHEEL
vdwlib-0.3.0.dist-info/top_level.txt
vdwlib-0.3.0.dist-info/RECORD
