Metadata-Version: 2.1
Name: vdwlib
Version: 0.3.0
Summary: Van der Waals radii library
Home-page: https://sebastianwellig.github.io/vdwlib
Download-URL: https://github.com/SebastianWellig/vdwlib
Author: Sebastian Wellig
License: GPL-2.0-only
Platform: UNKNOWN
